inference/.gitattributes
inference/app.py
inference/benchmark.py
inference/config.ini
inference/draw.ipynb
inference/report/report_2024-10-31_11-53-34.html
inference/report/report_2024-10-31_13-03-08.html
inference/report/report_2024-10-31_13-59-19.html
inference/report/report_2024-10-31_14-07-18.html
inference/util.py
ai_benchmarks-0.2.0.dist-info/entry_points.txt
ai_benchmarks-0.2.0.dist-info/METADATA
ai_benchmarks-0.2.0.dist-info/WHEEL
ai_benchmarks-0.2.0.dist-info/RECORD
