Metadata-Version: 2.1
Name: ai-benchmarks
Version: 0.2.0
Summary: HS-QA
Author: wangyue
Requires-Python: >=3.9,<4.0
Classifier: Programming Language :: Python :: 3
Classifier: Programming Language :: Python :: 3.9
Classifier: Programming Language :: Python :: 3.10
Classifier: Programming Language :: Python :: 3.11
Classifier: Programming Language :: Python :: 3.12
Classifier: Programming Language :: Python :: 3.13
Requires-Dist: aiofiles
Requires-Dist: fastapi
Requires-Dist: openai
Requires-Dist: orjson
Requires-Dist: paramiko
Requires-Dist: prettytable
Requires-Dist: requests
Requires-Dist: starlette
Requires-Dist: uvicorn
